DependancyNeedle/__init__.py
DependancyNeedle/container/__init__.py
DependancyNeedle/container/di_container.py
DependancyNeedle-0.0.1.dist-info/METADATA
DependancyNeedle-0.0.1.dist-info/WHEEL
DependancyNeedle-0.0.1.dist-info/top_level.txt
DependancyNeedle-0.0.1.dist-info/RECORD
